Audio_Cdvst/__init__.py
Audio_Cdvst/tempCodeRunnerFile.py
Audio_Cdvst-1.0.dist-info/METADATA
Audio_Cdvst-1.0.dist-info/WHEEL
Audio_Cdvst-1.0.dist-info/top_level.txt
Audio_Cdvst-1.0.dist-info/RECORD
