Metadata-Version: 2.1
Name: Audio-Cdvst
Version: 1.0
Summary: Eine Python-Bibliothek zur einfachen Audiowiedergabe und -aufnahme.
Home-page: https://now4free.de/python/module/Audio_Cdvst
Author: Philipp Juen
Author-email: support@now4free.de
License: MIT
Project-URL: Source, https://github.com/philippjuen/Audio_Cdvst
Keywords: audio,playback,recording,language recognition
Classifier: Development Status :: 3 - Alpha
Classifier: Intended Audience :: Developers
Classifier: License :: OSI Approved :: MIT License
Classifier: Programming Language :: Python :: 3
Classifier: Programming Language :: Python :: 3.6
Classifier: Programming Language :: Python :: 3.7
Classifier: Programming Language :: Python :: 3.8
Classifier: Programming Language :: Python :: 3.9
Requires-Dist: pydub
Requires-Dist: SpeechRecognition
